conntask_ni/.DS_Store
conntask_ni/__init__.py
conntask_ni/extract_features.py
conntask_ni/files/Schaefer2018_100Parcels_7Networks_order.dtseries.nii
conntask_ni/files/example.dtseries.nii
conntask_ni/files/ica_both_hemis_45_comp_cleaned.dtseries.nii
conntask_ni/model_and_predict.py
conntask_ni/utils.py
conntask_ni-0.1.4.dist-info/WHEEL
conntask_ni-0.1.4.dist-info/METADATA
conntask_ni-0.1.4.dist-info/RECORD
