Metadata-Version: 2.1
Name: conntask-ni
Version: 0.1.4
Summary: 
Author: shachar_gal
Author-email: gal.shachar@gmail.com
Requires-Python: >=3.9,<4.0
Classifier: Programming Language :: Python :: 3
Classifier: Programming Language :: Python :: 3.9
Requires-Dist: nibabel (>=3.2.1,<4.0.0)
Requires-Dist: numpy (>=1.21.1,<2.0.0)
Requires-Dist: pandas (>=1.3.0,<2.0.0)
Requires-Dist: scikit-learn (>=0.24.2,<0.25.0)
Requires-Dist: scipy (>=1.7.0,<2.0.0)
